lattice/__init__.py
lattice/exceptions.py
lattice/execution.py
lattice/factory.py
lattice/graph.py
lattice/pool.py
lattice/storage.py
lattice/types.py
lattice/utils.py
lattice_client-0.1.0.dist-info/METADATA
lattice_client-0.1.0.dist-info/WHEEL
lattice_client-0.1.0.dist-info/top_level.txt
lattice_client-0.1.0.dist-info/RECORD
