Metadata-Version: 2.1
Name: lattice-client
Version: 0.1.0
Summary: UNKNOWN
Home-page: UNKNOWN
License: UNKNOWN
Platform: UNKNOWN
Requires-Dist: cloudpickle (==2.2.1)
Requires-Dist: httpx (==0.24.0)
Requires-Dist: networkx (==3.1)
Requires-Dist: requests (==2.26.0)
Requires-Dist: rich (==13.3.5)
